chocolate_app-9.1.0.dist-info/METADATA
chocolate_app-9.1.0.dist-info/WHEEL
chocolate_app-9.1.0.dist-info/entry_points.txt
chocolate_app/.mypy_cache/.gitignore
chocolate_app/.mypy_cache/3.10/@plugins_snapshot.json
chocolate_app/.mypy_cache/3.10/Levenshtein/__init__.data.json
chocolate_app/.mypy_cache/3.10/Levenshtein/__init__.meta.json
chocolate_app/.mypy_cache/3.10/PIL/Image.data.json
chocolate_app/.mypy_cache/3.10/PIL/Image.meta.json
chocolate_app/.mypy_cache/3.10/PIL/ImageColor.data.json
chocolate_app/.mypy_cache/3.10/PIL/ImageColor.meta.json
chocolate_app/.mypy_cache/3.10/PIL/ImageDraw.data.json
chocolate_app/.mypy_cache/3.10/PIL/ImageDraw.meta.json
chocolate_app/.mypy_cache/3.10/PIL/ImageFilter.data.json
chocolate_app/.mypy_cache/3.10/PIL/ImageFilter.meta.json
chocolate_app/.mypy_cache/3.10/PIL/ImageFont.data.json
chocolate_app/.mypy_cache/3.10/PIL/ImageFont.meta.json
chocolate_app/.mypy_cache/3.10/PIL/ImagePalette.data.json
chocolate_app/.mypy_cache/3.10/PIL/ImagePalette.meta.json
chocolate_app/.mypy_cache/3.10/PIL/PyAccess.data.json
chocolate_app/.mypy_cache/3.10/PIL/PyAccess.meta.json
chocolate_app/.mypy_cache/3.10/PIL/__init__.data.json
chocolate_app/.mypy_cache/3.10/PIL/__init__.meta.json
chocolate_app/.mypy_cache/3.10/PIL/_imaging.data.json
chocolate_app/.mypy_cache/3.10/PIL/_imaging.meta.json
chocolate_app/.mypy_cache/3.10/__future__.data.json
chocolate_app/.mypy_cache/3.10/__future__.meta.json
chocolate_app/.mypy_cache/3.10/_ast.data.json
chocolate_app/.mypy_cache/3.10/_ast.meta.json
chocolate_app/.mypy_cache/3.10/_codecs.data.json
chocolate_app/.mypy_cache/3.10/_codecs.meta.json
chocolate_app/.mypy_cache/3.10/_collections_abc.data.json
chocolate_app/.mypy_cache/3.10/_collections_abc.meta.json
chocolate_app/.mypy_cache/3.10/_compression.data.json
chocolate_app/.mypy_cache/3.10/_compression.meta.json
chocolate_app/.mypy_cache/3.10/_ctypes.data.json
chocolate_app/.mypy_cache/3.10/_ctypes.meta.json
chocolate_app/.mypy_cache/3.10/_decimal.data.json
chocolate_app/.mypy_cache/3.10/_decimal.meta.json
chocolate_app/.mypy_cache/3.10/_locale.data.json
chocolate_app-9.1.0.dist-info/RECORD
