Metadata-Version: 2.1
Name: chocolate_app
Version: 9.1.0
Author-Email: Imprevisible <impr.visible@gmail.com>, Impre-visible <impr.visible@gmail.com>
License: GPL-3.0
Requires-Python: >=3.9
Requires-Dist: colorama==0.4.5
Requires-Dist: deep-translator==1.10.1
Requires-Dist: Flask==2.2.2
Requires-Dist: Flask-Cors==3.0.10
Requires-Dist: flask-login==0.6.2
Requires-Dist: flask-sqlalchemy==3.0.3
Requires-Dist: get-video-properties==0.1.1
Requires-Dist: GitPython==3.1.31
Requires-Dist: GPUtil==1.4.0
Requires-Dist: guessit==3.7.1
Requires-Dist: ImageHash==4.3.1
Requires-Dist: opencv-python==4.5.5.64
Requires-Dist: Pillow==9.5.0
Requires-Dist: pyarr==5.0.0
Requires-Dist: pycountry==22.3.5
Requires-Dist: PyPDF2==3.0.1
Requires-Dist: pypresence==4.2.1
Requires-Dist: python-Levenshtein==0.20.9
Requires-Dist: rarfile==4.0
Requires-Dist: SQLAlchemy==1.4.45
Requires-Dist: Unidecode==1.3.6
Requires-Dist: Werkzeug==2.2.2
Requires-Dist: deezer-python>=6.1.0
Requires-Dist: tinytag>=1.9.0
Requires-Dist: argparse>=1.4.0
Requires-Dist: EbookLib>=0.18
Requires-Dist: flask-migrate>=4.0.4
Requires-Dist: tmdbv3api>=1.9.0
Requires-Dist: natsort>=8.4.0
Requires-Dist: PyMuPdf>=1.22.5
Requires-Dist: pyyaml>=6.0.1
Requires-Dist: jsbeautifier>=1.15.1
Requires-Dist: moviepy>=1.0.3
Requires-Dist: pydub>=0.25.1
Requires-Dist: matplotlib>=3.8.3
Requires-Dist: dtw>=1.4.0
Requires-Dist: audio-similarity==1.0.0
Requires-Dist: faiss-cpu>=1.8.0
Requires-Dist: ffmpeg>=1.4
Requires-Dist: pandas>=2.2.1
